{
  "project_info": {
    "project_number": "1087758920414",
    "project_id": "flutterstarter-83233",
    "storage_bucket": "flutterstarter-83233.appspot.com"
  },
  "client": [
    {
      "client_info": {
        "mobilesdk_app_id": "1:1087758920414:android:fadbd3c03a8182ebb3f04f",
        "android_client_info": {
          "package_name": "com.flutterstarter.app"
        }
      },
      "oauth_client": [
        {
          "client_id": "1087758920414-5r8rharevd0jtnoa2dde4irtqnhn8t3t.apps.googleusercontent.com",
          "client_type": 3
        }
      ],
      "api_key": [
        {
          "current_key": "AIzaSyAY86ireslITmHsd-h8qWP4ewnEJnkCM7Q"
        }
      ],
      "services": {
        "appinvite_service": {
          "other_platform_oauth_client": [
            {
              "client_id": "1087758920414-5r8rharevd0jtnoa2dde4irtqnhn8t3t.apps.googleusercontent.com",
              "client_type": 3
            }
          ]
        }
      }
    }
  ],
  "configuration_version": "1"
}